{
  "metadata": {
    "generated_at": "2026-03-20T05:31:34.324966",
    "city": "Nagpur",
    "system": "Nagpur Metro"
  },
  "lines": [
    {
      "id": "orange-line",
      "name": "Orange Line (NS)",
      "color": [
        255,
        120,
        0
      ],
      "path": [
        [
          79.0882,
          21.2
        ],
        [
          79.0882,
          21.192
        ],
        [
          79.0882,
          21.185
        ],
        [
          79.0882,
          21.178
        ],
        [
          79.0882,
          21.17
        ],
        [
          79.0882,
          21.162
        ],
        [
          79.0882,
          21.154
        ],
        [
          79.0882,
          21.1458
        ],
        [
          79.0882,
          21.138
        ],
        [
          79.0882,
          21.13
        ],
        [
          79.0882,
          21.115
        ],
        [
          79.0882,
          21.105
        ],
        [
          79.0882,
          21.095
        ],
        [
          79.0882,
          21.088
        ],
        [
          79.0882,
          21.08
        ],
        [
          79.0882,
          21.072
        ],
        [
          79.0882,
          21.065
        ],
        [
          79.0882,
          21.06
        ]
      ]
    },
    {
      "id": "aqua-line",
      "name": "Aqua Line (EW)",
      "color": [
        0,
        180,
        255
      ],
      "path": [
        [
          79.135,
          21.1458
        ],
        [
          79.128,
          21.1458
        ],
        [
          79.121,
          21.1458
        ],
        [
          79.115,
          21.1458
        ],
        [
          79.108,
          21.1458
        ],
        [
          79.095,
          21.1458
        ],
        [
          79.0882,
          21.1458
        ],
        [
          79.075,
          21.1458
        ],
        [
          79.068,
          21.1458
        ],
        [
          79.06,
          21.1458
        ],
        [
          79.052,
          21.1458
        ],
        [
          79.045,
          21.1458
        ],
        [
          79.04,
          21.1458
        ],
        [
          79.032,
          21.1458
        ],
        [
          79.025,
          21.1458
        ],
        [
          79.015,
          21.1458
        ]
      ]
    }
  ],
  "stations": [
    {
      "id": "station-o-automotive-square",
      "name": "Automotive Square",
      "line": "Orange",
      "coords": [
        79.0882,
        21.2
      ],
      "occupancy": 36.0036398100326,
      "status": "Operational",
      "ridership": 2407
    },
    {
      "id": "station-o-nari-road",
      "name": "Nari Road",
      "line": "Orange",
      "coords": [
        79.0882,
        21.192
      ],
      "occupancy": 33.41552015509484,
      "status": "Operational",
      "ridership": 1521
    },
    {
      "id": "station-o-indora-square",
      "name": "Indora Square",
      "line": "Orange",
      "coords": [
        79.0882,
        21.185
      ],
      "occupancy": 91.678255152818,
      "status": "Operational",
      "ridership": 2862
    },
    {
      "id": "station-o-kadvi-chowk",
      "name": "Kadvi Chowk",
      "line": "Orange",
      "coords": [
        79.0882,
        21.178
      ],
      "occupancy": 50.01720455551009,
      "status": "Operational",
      "ridership": 2660
    },
    {
      "id": "station-o-gaddigodam-square",
      "name": "Gaddigodam Square",
      "line": "Orange",
      "coords": [
        79.0882,
        21.17
      ],
      "occupancy": 87.30417352408877,
      "status": "Operational",
      "ridership": 843
    },
    {
      "id": "station-o-kasturchand-park",
      "name": "Kasturchand Park",
      "line": "Orange",
      "coords": [
        79.0882,
        21.162
      ],
      "occupancy": 38.72875420283902,
      "status": "Operational",
      "ridership": 1582
    },
    {
      "id": "station-o-zero-mile",
      "name": "Zero Mile",
      "line": "Orange",
      "coords": [
        79.0882,
        21.154
      ],
      "occupancy": 89.09953596087774,
      "status": "Operational",
      "ridership": 1318
    },
    {
      "id": "station-o-sitabuldi-interchange",
      "name": "Sitabuldi Interchange",
      "line": "Interchange",
      "coords": [
        79.0882,
        21.1458
      ],
      "occupancy": 76.36877722418993,
      "status": "Operational",
      "ridership": 2355
    },
    {
      "id": "station-o-congress-nagar",
      "name": "Congress Nagar",
      "line": "Orange",
      "coords": [
        79.0882,
        21.138
      ],
      "occupancy": 26.737688993538526,
      "status": "Operational",
      "ridership": 3459
    },
    {
      "id": "station-o-rahate-colony",
      "name": "Rahate Colony",
      "line": "Orange",
      "coords": [
        79.0882,
        21.13
      ],
      "occupancy": 61.879766589540075,
      "status": "Operational",
      "ridership": 2080
    },
    {
      "id": "station-o-ajni-square",
      "name": "Ajni Square",
      "line": "Orange",
      "coords": [
        79.0882,
        21.115
      ],
      "occupancy": 45.876337937534416,
      "status": "Operational",
      "ridership": 1870
    },
    {
      "id": "station-o-chhatrapati-square",
      "name": "Chhatrapati Square",
      "line": "Orange",
      "coords": [
        79.0882,
        21.105
      ],
      "occupancy": 71.13193259354493,
      "status": "Operational",
      "ridership": 520
    },
    {
      "id": "station-o-jaiprakash-nagar",
      "name": "Jaiprakash Nagar",
      "line": "Orange",
      "coords": [
        79.0882,
        21.095
      ],
      "occupancy": 20.16716444907341,
      "status": "Operational",
      "ridership": 3191
    },
    {
      "id": "station-o-ujjwal-nagar",
      "name": "Ujjwal Nagar",
      "line": "Orange",
      "coords": [
        79.0882,
        21.088
      ],
      "occupancy": 87.75153222880894,
      "status": "Operational",
      "ridership": 2402
    },
    {
      "id": "station-o-airport",
      "name": "Airport",
      "line": "Orange",
      "coords": [
        79.0882,
        21.08
      ],
      "occupancy": 55.20799147892388,
      "status": "Operational",
      "ridership": 2739
    },
    {
      "id": "station-o-airport-south",
      "name": "Airport South",
      "line": "Orange",
      "coords": [
        79.0882,
        21.072
      ],
      "occupancy": 55.1818608383792,
      "status": "Operational",
      "ridership": 3026
    },
    {
      "id": "station-o-new-airport",
      "name": "New Airport",
      "line": "Orange",
      "coords": [
        79.0882,
        21.065
      ],
      "occupancy": 48.42472517523446,
      "status": "Operational",
      "ridership": 3248
    },
    {
      "id": "station-o-khapri",
      "name": "Khapri",
      "line": "Orange",
      "coords": [
        79.0882,
        21.06
      ],
      "occupancy": 42.38308221072085,
      "status": "Operational",
      "ridership": 1219
    },
    {
      "id": "station-a-prajapati-nagar",
      "name": "Prajapati Nagar",
      "line": "Aqua",
      "coords": [
        79.135,
        21.1458
      ],
      "occupancy": 57.47494041361829,
      "status": "Operational",
      "ridership": 1679
    },
    {
      "id": "station-a-vaishno-devi-chowk",
      "name": "Vaishno Devi Chowk",
      "line": "Aqua",
      "coords": [
        79.128,
        21.1458
      ],
      "occupancy": 39.65721387828071,
      "status": "Operational",
      "ridership": 1717
    },
    {
      "id": "station-a-ambedkar-square",
      "name": "Ambedkar Square",
      "line": "Aqua",
      "coords": [
        79.121,
        21.1458
      ],
      "occupancy": 25.854274317973367,
      "status": "Operational",
      "ridership": 2492
    },
    {
      "id": "station-a-telephone-exchange",
      "name": "Telephone Exchange",
      "line": "Aqua",
      "coords": [
        79.115,
        21.1458
      ],
      "occupancy": 48.05808626397919,
      "status": "Operational",
      "ridership": 3279
    },
    {
      "id": "station-a-chittaroli-square",
      "name": "Chittaroli Square",
      "line": "Aqua",
      "coords": [
        79.108,
        21.1458
      ],
      "occupancy": 78.37254044551634,
      "status": "Operational",
      "ridership": 766
    },
    {
      "id": "station-a-dosar-vaisya-square",
      "name": "Dosar Vaisya Square",
      "line": "Aqua",
      "coords": [
        79.095,
        21.1458
      ],
      "occupancy": 58.124899544825595,
      "status": "Operational",
      "ridership": 2408
    },
    {
      "id": "station-a-jhansi-rani-square",
      "name": "Jhansi Rani Square",
      "line": "Aqua",
      "coords": [
        79.075,
        21.1458
      ],
      "occupancy": 62.615894240517996,
      "status": "Operational",
      "ridership": 1091
    },
    {
      "id": "station-a-institution-of-engineers",
      "name": "Institution of Engineers",
      "line": "Aqua",
      "coords": [
        79.068,
        21.1458
      ],
      "occupancy": 40.51154636267053,
      "status": "Operational",
      "ridership": 2583
    },
    {
      "id": "station-a-shankar-nagar-square",
      "name": "Shankar Nagar Square",
      "line": "Aqua",
      "coords": [
        79.06,
        21.1458
      ],
      "occupancy": 72.12318046544817,
      "status": "Operational",
      "ridership": 3437
    },
    {
      "id": "station-a-lad-college",
      "name": "Lad College",
      "line": "Aqua",
      "coords": [
        79.052,
        21.1458
      ],
      "occupancy": 52.5395232129973,
      "status": "Operational",
      "ridership": 1075
    },
    {
      "id": "station-a-dharampeth-college",
      "name": "Dharampeth College",
      "line": "Aqua",
      "coords": [
        79.045,
        21.1458
      ],
      "occupancy": 36.139381352554715,
      "status": "Maintenance",
      "ridership": 938
    },
    {
      "id": "station-a-subhash-nagar",
      "name": "Subhash Nagar",
      "line": "Aqua",
      "coords": [
        79.04,
        21.1458
      ],
      "occupancy": 22.219337402633382,
      "status": "Operational",
      "ridership": 3296
    },
    {
      "id": "station-a-rachana-ring-road",
      "name": "Rachana Ring Road",
      "line": "Aqua",
      "coords": [
        79.032,
        21.1458
      ],
      "occupancy": 77.9759791831335,
      "status": "Operational",
      "ridership": 3269
    },
    {
      "id": "station-a-vasudev-nagar",
      "name": "Vasudev Nagar",
      "line": "Aqua",
      "coords": [
        79.025,
        21.1458
      ],
      "occupancy": 79.36673265701953,
      "status": "Operational",
      "ridership": 1200
    },
    {
      "id": "station-a-lokmanya-nagar",
      "name": "Lokmanya Nagar",
      "line": "Aqua",
      "coords": [
        79.015,
        21.1458
      ],
      "occupancy": 50.81299280828109,
      "status": "Operational",
      "ridership": 717
    }
  ],
  "trains": [
    {
      "id": "train-orange-0",
      "line": "Orange",
      "color": [
        255,
        165,
        0
      ],
      "path": [
        [
          79.0882,
          21.1458
        ],
        [
          79.0882,
          21.138
        ]
      ],
      "timestamps": [
        0,
        300
      ]
    },
    {
      "id": "train-orange-1",
      "line": "Orange",
      "color": [
        255,
        165,
        0
      ],
      "path": [
        [
          79.0882,
          21.138
        ],
        [
          79.0882,
          21.13
        ]
      ],
      "timestamps": [
        300,
        600
      ]
    },
    {
      "id": "train-orange-2",
      "line": "Orange",
      "color": [
        255,
        165,
        0
      ],
      "path": [
        [
          79.0882,
          21.185
        ],
        [
          79.0882,
          21.178
        ]
      ],
      "timestamps": [
        600,
        900
      ]
    },
    {
      "id": "train-aqua-0",
      "line": "Aqua",
      "color": [
        0,
        200,
        255
      ],
      "path": [
        [
          79.108,
          21.1458
        ],
        [
          79.095,
          21.1458
        ]
      ],
      "timestamps": [
        100,
        500
      ]
    },
    {
      "id": "train-aqua-1",
      "line": "Aqua",
      "color": [
        0,
        200,
        255
      ],
      "path": [
        [
          79.128,
          21.1458
        ],
        [
          79.121,
          21.1458
        ]
      ],
      "timestamps": [
        500,
        900
      ]
    },
    {
      "id": "train-aqua-2",
      "line": "Aqua",
      "color": [
        0,
        200,
        255
      ],
      "path": [
        [
          79.045,
          21.1458
        ],
        [
          79.04,
          21.1458
        ]
      ],
      "timestamps": [
        900,
        1300
      ]
    }
  ],
  "history": [
    {
      "time": "00:00",
      "ridership": 1044,
      "capacity": 6000
    },
    {
      "time": "02:00",
      "ridership": 1360,
      "capacity": 6000
    },
    {
      "time": "04:00",
      "ridership": 1170,
      "capacity": 6000
    },
    {
      "time": "06:00",
      "ridership": 1016,
      "capacity": 6000
    },
    {
      "time": "08:00",
      "ridership": 4649,
      "capacity": 6000
    },
    {
      "time": "10:00",
      "ridership": 4095,
      "capacity": 6000
    },
    {
      "time": "12:00",
      "ridership": 1584,
      "capacity": 6000
    },
    {
      "time": "14:00",
      "ridership": 1683,
      "capacity": 6000
    },
    {
      "time": "16:00",
      "ridership": 1012,
      "capacity": 6000
    },
    {
      "time": "18:00",
      "ridership": 5258,
      "capacity": 6000
    },
    {
      "time": "20:00",
      "ridership": 1299,
      "capacity": 6000
    },
    {
      "time": "22:00",
      "ridership": 1699,
      "capacity": 6000
    }
  ]
}