{
  "metadata": {
    "generated_at": "2026-03-15T14:05:36.168754",
    "city": "Nagpur",
    "system": "Nagpur Metro"
  },
  "lines": [
    {
      "id": "orange-line",
      "name": "Orange Line (NS)",
      "color": [
        255,
        120,
        0
      ],
      "path": [
        [
          79.0882,
          21.2
        ],
        [
          79.0882,
          21.192
        ],
        [
          79.0882,
          21.185
        ],
        [
          79.0882,
          21.178
        ],
        [
          79.0882,
          21.17
        ],
        [
          79.0882,
          21.162
        ],
        [
          79.0882,
          21.154
        ],
        [
          79.0882,
          21.1458
        ],
        [
          79.0882,
          21.138
        ],
        [
          79.0882,
          21.13
        ],
        [
          79.0882,
          21.115
        ],
        [
          79.0882,
          21.105
        ],
        [
          79.0882,
          21.095
        ],
        [
          79.0882,
          21.088
        ],
        [
          79.0882,
          21.08
        ],
        [
          79.0882,
          21.072
        ],
        [
          79.0882,
          21.065
        ],
        [
          79.0882,
          21.06
        ]
      ]
    },
    {
      "id": "aqua-line",
      "name": "Aqua Line (EW)",
      "color": [
        0,
        180,
        255
      ],
      "path": [
        [
          79.135,
          21.1458
        ],
        [
          79.128,
          21.1458
        ],
        [
          79.121,
          21.1458
        ],
        [
          79.115,
          21.1458
        ],
        [
          79.108,
          21.1458
        ],
        [
          79.095,
          21.1458
        ],
        [
          79.0882,
          21.1458
        ],
        [
          79.075,
          21.1458
        ],
        [
          79.068,
          21.1458
        ],
        [
          79.06,
          21.1458
        ],
        [
          79.052,
          21.1458
        ],
        [
          79.045,
          21.1458
        ],
        [
          79.04,
          21.1458
        ],
        [
          79.032,
          21.1458
        ],
        [
          79.025,
          21.1458
        ],
        [
          79.015,
          21.1458
        ]
      ]
    }
  ],
  "stations": [
    {
      "id": "station-o-automotive-square",
      "name": "Automotive Square",
      "line": "Orange",
      "coords": [
        79.0882,
        21.2
      ],
      "occupancy": 22.1972311269605,
      "status": "Operational",
      "ridership": 647
    },
    {
      "id": "station-o-nari-road",
      "name": "Nari Road",
      "line": "Orange",
      "coords": [
        79.0882,
        21.192
      ],
      "occupancy": 53.623458063372574,
      "status": "Operational",
      "ridership": 2742
    },
    {
      "id": "station-o-indora-square",
      "name": "Indora Square",
      "line": "Orange",
      "coords": [
        79.0882,
        21.185
      ],
      "occupancy": 32.44200129095006,
      "status": "Operational",
      "ridership": 1385
    },
    {
      "id": "station-o-kadvi-chowk",
      "name": "Kadvi Chowk",
      "line": "Orange",
      "coords": [
        79.0882,
        21.178
      ],
      "occupancy": 82.27870809181806,
      "status": "Operational",
      "ridership": 537
    },
    {
      "id": "station-o-gaddigodam-square",
      "name": "Gaddigodam Square",
      "line": "Orange",
      "coords": [
        79.0882,
        21.17
      ],
      "occupancy": 92.07285505148522,
      "status": "Operational",
      "ridership": 2270
    },
    {
      "id": "station-o-kasturchand-park",
      "name": "Kasturchand Park",
      "line": "Orange",
      "coords": [
        79.0882,
        21.162
      ],
      "occupancy": 44.9072472954855,
      "status": "Operational",
      "ridership": 1220
    },
    {
      "id": "station-o-zero-mile",
      "name": "Zero Mile",
      "line": "Orange",
      "coords": [
        79.0882,
        21.154
      ],
      "occupancy": 63.427035005707346,
      "status": "Operational",
      "ridership": 1596
    },
    {
      "id": "station-o-sitabuldi-interchange",
      "name": "Sitabuldi Interchange",
      "line": "Interchange",
      "coords": [
        79.0882,
        21.1458
      ],
      "occupancy": 61.436747189730845,
      "status": "Operational",
      "ridership": 3142
    },
    {
      "id": "station-o-congress-nagar",
      "name": "Congress Nagar",
      "line": "Orange",
      "coords": [
        79.0882,
        21.138
      ],
      "occupancy": 72.10696839249728,
      "status": "Operational",
      "ridership": 1853
    },
    {
      "id": "station-o-rahate-colony",
      "name": "Rahate Colony",
      "line": "Orange",
      "coords": [
        79.0882,
        21.13
      ],
      "occupancy": 73.20206457562713,
      "status": "Operational",
      "ridership": 2528
    },
    {
      "id": "station-o-ajni-square",
      "name": "Ajni Square",
      "line": "Orange",
      "coords": [
        79.0882,
        21.115
      ],
      "occupancy": 24.497351787739817,
      "status": "Operational",
      "ridership": 854
    },
    {
      "id": "station-o-chhatrapati-square",
      "name": "Chhatrapati Square",
      "line": "Orange",
      "coords": [
        79.0882,
        21.105
      ],
      "occupancy": 64.54287075118151,
      "status": "Operational",
      "ridership": 878
    },
    {
      "id": "station-o-jaiprakash-nagar",
      "name": "Jaiprakash Nagar",
      "line": "Orange",
      "coords": [
        79.0882,
        21.095
      ],
      "occupancy": 50.88844584709162,
      "status": "Operational",
      "ridership": 3229
    },
    {
      "id": "station-o-ujjwal-nagar",
      "name": "Ujjwal Nagar",
      "line": "Orange",
      "coords": [
        79.0882,
        21.088
      ],
      "occupancy": 35.7865463846078,
      "status": "Operational",
      "ridership": 1702
    },
    {
      "id": "station-o-airport",
      "name": "Airport",
      "line": "Orange",
      "coords": [
        79.0882,
        21.08
      ],
      "occupancy": 61.66198468306661,
      "status": "Operational",
      "ridership": 1292
    },
    {
      "id": "station-o-airport-south",
      "name": "Airport South",
      "line": "Orange",
      "coords": [
        79.0882,
        21.072
      ],
      "occupancy": 36.5567229336832,
      "status": "Operational",
      "ridership": 1971
    },
    {
      "id": "station-o-new-airport",
      "name": "New Airport",
      "line": "Orange",
      "coords": [
        79.0882,
        21.065
      ],
      "occupancy": 43.7578072672342,
      "status": "Operational",
      "ridership": 3339
    },
    {
      "id": "station-o-khapri",
      "name": "Khapri",
      "line": "Orange",
      "coords": [
        79.0882,
        21.06
      ],
      "occupancy": 79.28310040230325,
      "status": "Operational",
      "ridership": 2225
    },
    {
      "id": "station-a-prajapati-nagar",
      "name": "Prajapati Nagar",
      "line": "Aqua",
      "coords": [
        79.135,
        21.1458
      ],
      "occupancy": 73.81747189041684,
      "status": "Operational",
      "ridership": 2566
    },
    {
      "id": "station-a-vaishno-devi-chowk",
      "name": "Vaishno Devi Chowk",
      "line": "Aqua",
      "coords": [
        79.128,
        21.1458
      ],
      "occupancy": 62.70411466498411,
      "status": "Maintenance",
      "ridership": 2286
    },
    {
      "id": "station-a-ambedkar-square",
      "name": "Ambedkar Square",
      "line": "Aqua",
      "coords": [
        79.121,
        21.1458
      ],
      "occupancy": 83.60756881484066,
      "status": "Operational",
      "ridership": 2837
    },
    {
      "id": "station-a-telephone-exchange",
      "name": "Telephone Exchange",
      "line": "Aqua",
      "coords": [
        79.115,
        21.1458
      ],
      "occupancy": 83.9882403069557,
      "status": "Operational",
      "ridership": 1049
    },
    {
      "id": "station-a-chittaroli-square",
      "name": "Chittaroli Square",
      "line": "Aqua",
      "coords": [
        79.108,
        21.1458
      ],
      "occupancy": 86.5963269204228,
      "status": "Operational",
      "ridership": 950
    },
    {
      "id": "station-a-dosar-vaisya-square",
      "name": "Dosar Vaisya Square",
      "line": "Aqua",
      "coords": [
        79.095,
        21.1458
      ],
      "occupancy": 87.97301562230896,
      "status": "Operational",
      "ridership": 1923
    },
    {
      "id": "station-a-jhansi-rani-square",
      "name": "Jhansi Rani Square",
      "line": "Aqua",
      "coords": [
        79.075,
        21.1458
      ],
      "occupancy": 46.550963617295494,
      "status": "Operational",
      "ridership": 568
    },
    {
      "id": "station-a-institution-of-engineers",
      "name": "Institution of Engineers",
      "line": "Aqua",
      "coords": [
        79.068,
        21.1458
      ],
      "occupancy": 32.111665525683634,
      "status": "Operational",
      "ridership": 1007
    },
    {
      "id": "station-a-shankar-nagar-square",
      "name": "Shankar Nagar Square",
      "line": "Aqua",
      "coords": [
        79.06,
        21.1458
      ],
      "occupancy": 87.50207886124885,
      "status": "Operational",
      "ridership": 2692
    },
    {
      "id": "station-a-lad-college",
      "name": "Lad College",
      "line": "Aqua",
      "coords": [
        79.052,
        21.1458
      ],
      "occupancy": 69.51227673489873,
      "status": "Operational",
      "ridership": 1477
    },
    {
      "id": "station-a-dharampeth-college",
      "name": "Dharampeth College",
      "line": "Aqua",
      "coords": [
        79.045,
        21.1458
      ],
      "occupancy": 27.677383266765517,
      "status": "Operational",
      "ridership": 2364
    },
    {
      "id": "station-a-subhash-nagar",
      "name": "Subhash Nagar",
      "line": "Aqua",
      "coords": [
        79.04,
        21.1458
      ],
      "occupancy": 68.06987403327983,
      "status": "Operational",
      "ridership": 2157
    },
    {
      "id": "station-a-rachana-ring-road",
      "name": "Rachana Ring Road",
      "line": "Aqua",
      "coords": [
        79.032,
        21.1458
      ],
      "occupancy": 81.04555185990404,
      "status": "Maintenance",
      "ridership": 3011
    },
    {
      "id": "station-a-vasudev-nagar",
      "name": "Vasudev Nagar",
      "line": "Aqua",
      "coords": [
        79.025,
        21.1458
      ],
      "occupancy": 54.439481534198016,
      "status": "Operational",
      "ridership": 864
    },
    {
      "id": "station-a-lokmanya-nagar",
      "name": "Lokmanya Nagar",
      "line": "Aqua",
      "coords": [
        79.015,
        21.1458
      ],
      "occupancy": 67.02577302929797,
      "status": "Operational",
      "ridership": 1374
    }
  ],
  "trains": [
    {
      "id": "train-orange-0",
      "line": "Orange",
      "color": [
        255,
        165,
        0
      ],
      "path": [
        [
          79.0882,
          21.1458
        ],
        [
          79.0882,
          21.138
        ]
      ],
      "timestamps": [
        0,
        300
      ]
    },
    {
      "id": "train-orange-1",
      "line": "Orange",
      "color": [
        255,
        165,
        0
      ],
      "path": [
        [
          79.0882,
          21.105
        ],
        [
          79.0882,
          21.095
        ]
      ],
      "timestamps": [
        300,
        600
      ]
    },
    {
      "id": "train-orange-2",
      "line": "Orange",
      "color": [
        255,
        165,
        0
      ],
      "path": [
        [
          79.0882,
          21.065
        ],
        [
          79.0882,
          21.06
        ]
      ],
      "timestamps": [
        600,
        900
      ]
    },
    {
      "id": "train-aqua-0",
      "line": "Aqua",
      "color": [
        0,
        200,
        255
      ],
      "path": [
        [
          79.075,
          21.1458
        ],
        [
          79.068,
          21.1458
        ]
      ],
      "timestamps": [
        100,
        500
      ]
    },
    {
      "id": "train-aqua-1",
      "line": "Aqua",
      "color": [
        0,
        200,
        255
      ],
      "path": [
        [
          79.115,
          21.1458
        ],
        [
          79.108,
          21.1458
        ]
      ],
      "timestamps": [
        500,
        900
      ]
    },
    {
      "id": "train-aqua-2",
      "line": "Aqua",
      "color": [
        0,
        200,
        255
      ],
      "path": [
        [
          79.04,
          21.1458
        ],
        [
          79.032,
          21.1458
        ]
      ],
      "timestamps": [
        900,
        1300
      ]
    }
  ],
  "history": [
    {
      "time": "00:00",
      "ridership": 871,
      "capacity": 6000
    },
    {
      "time": "02:00",
      "ridership": 1064,
      "capacity": 6000
    },
    {
      "time": "04:00",
      "ridership": 929,
      "capacity": 6000
    },
    {
      "time": "06:00",
      "ridership": 1451,
      "capacity": 6000
    },
    {
      "time": "08:00",
      "ridership": 4111,
      "capacity": 6000
    },
    {
      "time": "10:00",
      "ridership": 4053,
      "capacity": 6000
    },
    {
      "time": "12:00",
      "ridership": 721,
      "capacity": 6000
    },
    {
      "time": "14:00",
      "ridership": 935,
      "capacity": 6000
    },
    {
      "time": "16:00",
      "ridership": 1174,
      "capacity": 6000
    },
    {
      "time": "18:00",
      "ridership": 5318,
      "capacity": 6000
    },
    {
      "time": "20:00",
      "ridership": 1373,
      "capacity": 6000
    },
    {
      "time": "22:00",
      "ridership": 1639,
      "capacity": 6000
    }
  ]
}